Metadata-Version: 1.2
Name: fairsearchdeltr
Version: 1.0.1
Summary: A Python library for disparate exposure in ranking (a learning to rank approach)
Home-page: https://github.com/fair-search/fairsearchdeltr-python
Author: Ivan Kitanovski
Author-email: ivan.kitanovski@gmail.com
License: Apache 2.0
Keywords: search,fairness,deltr,disparate exposure in ranking,learning to rank
Platform: UNKNOWN
Classifier: Development Status :: 5 - Production/Stable
Classifier: Intended Audience :: Developers
Classifier: Natural Language :: English
Classifier: License :: OSI Approved :: Apache Software License
Classifier: Programming Language :: Python
Classifier: Programming Language :: Python :: 3
Classifier: Programming Language :: Python :: 3.4
Classifier: Programming Language :: Python :: 3.5
Classifier: Programming Language :: Python :: 3.6
Classifier: Programming Language :: Python :: 3.7
Classifier: Programming Language :: Python :: Implementation :: PyPy
Requires-Python: >=3.0
